lark/__init__.py
lark/common.py
lark/exceptions.py
lark/grammar.py
lark/indenter.py
lark/lark.py
lark/lexer.py
lark/load_grammar.py
lark/parse_tree_builder.py
lark/parser_frontends.py
lark/reconstruct.py
lark/reconstruct2.py
lark/tree.py
lark/tree_matcher.py
lark/utils.py
lark/visitors.py
lark/__pyinstaller/__init__.py
lark/__pyinstaller/hook-lark.py
lark/grammars/common.lark
lark/grammars/python.lark
lark/grammars/unicode.lark
lark/parsers/__init__.py
lark/parsers/cyk.py
lark/parsers/earley.py
lark/parsers/earley_common.py
lark/parsers/earley_forest.py
lark/parsers/grammar_analysis.py
lark/parsers/lalr_analysis.py
lark/parsers/lalr_parser.py
lark/parsers/lalr_puppet.py
lark/parsers/xearley.py
lark/tools/__init__.py
lark/tools/nearley.py
lark/tools/serialize.py
lark/tools/standalone.py
lark-stubs/__init__.pyi
lark-stubs/exceptions.pyi
lark-stubs/indenter.pyi
lark-stubs/lark.pyi
lark-stubs/lexer.pyi
lark-stubs/reconstruct.pyi
lark-stubs/tree.pyi
lark-stubs/visitors.pyi
lark_parser-0.11.1.dist-info/LICENSE
lark_parser-0.11.1.dist-info/METADATA
lark_parser-0.11.1.dist-info/WHEEL
lark_parser-0.11.1.dist-info/entry_points.txt
lark_parser-0.11.1.dist-info/top_level.txt
lark_parser-0.11.1.dist-info/RECORD
